{"is_source_file": true, "format": "JavaScript (React JSX)", "description": "React component for displaying detailed information about a specific book, fetched by ID from an API.", "external_files": ["../lib/api/books", "react", "react-router-dom"], "external_methods": ["getBook", "useParams", "Link"], "published": [], "classes": [], "methods": [{"name": "BookDetails()", "description": "React functional component that displays details of a book identified by route parameter.", "scope": "", "scopeKind": ""}, {"name": "load()", "scope": "BookDetails", "scopeKind": "function", "description": "unavailable"}], "calls": ["useParams", "useState", "useEffect", "getBook", "Link"], "search-terms": ["BookDetails", "getBook", "React", "useParams", "useState", "useEffect", "react-router-dom", "jsx", "book details"], "state": 2, "file_id": 26, "knowledge_revision": 60, "git_revision": "", "ctags": [{"_type": "tag", "name": "BookDetails", "path": "/home/kavia/workspace/code-generation/library-explorer-283657-283666/library_frontend/src/pages/BookDetails.jsx", "pattern": "/^export default function BookDetails() {$/", "language": "JavaScript", "kind": "function", "signature": "()"}, {"_type": "tag", "name": "load", "path": "/home/kavia/workspace/code-generation/library-explorer-283657-283666/library_frontend/src/pages/BookDetails.jsx", "pattern": "/^    async function load() {$/", "language": "JavaScript", "kind": "function", "signature": "()", "scope": "BookDetails", "scopeKind": "function"}], "hash": "6f43b74d4605f6fc51a5a4219ede6d15", "format-version": 4, "code-base-name": "library_frontend", "filename": "library_frontend/src/pages/BookDetails.jsx", "revision_history": [{"60": ""}]}